lpitabformer/__init__.py
lpitabformer/ft_transformer.py
lpitabformer/lpi_predict.py
lpitabformer/utils.py
lpitabformer-1.0.1.dist-info/LICENSE
lpitabformer-1.0.1.dist-info/METADATA
lpitabformer-1.0.1.dist-info/WHEEL
lpitabformer-1.0.1.dist-info/top_level.txt
lpitabformer-1.0.1.dist-info/RECORD
