Metadata-Version: 2.2
Name: lpitabformer
Version: 1.0.1
Summary: Lpitabformer
Home-page: https://github.com/Ci-TJ/LPItabformer
Author: linqin
Author-email: 1911449@tongji.edu.cn
Requires-Python: >=3.6
License-File: LICENSE
Dynamic: author
Dynamic: author-email
Dynamic: description
Dynamic: description-content-type
Dynamic: home-page
Dynamic: requires-python
Dynamic: summary
